client/__init__.py
client/client.py
exchanges/__init__.py
exchanges/constants.py
exchanges/errors.py
exchanges/exchange.py
exchanges/binance/__init__.py
exchanges/binance/binance.py
exchanges/binance/constants.py
exchanges/bittrex/__init__.py
exchanges/bittrex/bittrex.py
exchanges/bittrex/constants.py
global_errors/__init__.py
global_errors/errors.py
py_crypto-0.0.4.dist-info/METADATA
py_crypto-0.0.4.dist-info/RECORD
py_crypto-0.0.4.dist-info/WHEEL
py_crypto-0.0.4.dist-info/top_level.txt
pycrypto/__init__.py
pycrypto/client.py
trades/__init__.py
trades/constants.py
trades/trade.py
utils/__init__.py
utils/utils.py
