Metadata-Version: 2.1
Name: py-crypto
Version: 0.0.4
Summary: A cryptocurrency trading library for Python with current support for Binance and Bittrex.
Home-page: https://github.com/gokulk04/py-crypto
Author: Gokul Kumarresen
Author-email: gokul.kumarresen@outlook.com
License: UNKNOWN
Platform: UNKNOWN
Classifier: Programming Language :: Python :: 2
Classifier: License :: OSI Approved :: MIT License
Classifier: Operating System :: OS Independent
